{"nodes": [{"id": "14", "name": "Slice::constructRefPicList", "symbolSize": "20", "x": -363.8434673004698, "y": -52.70195470745, "category": 0, "url": "http://www.baidu.com", "description": "构造参考列表"}, {"id": "17", "name": "CodingStructure::traverseCUs", "symbolSize": "20", "x": -454.27990660343073, "y": -145.72575882353257, "category": 0, "url": "http://www.baidu.com", "description": "遍历CU"}, {"id": "35", "name": "InterPrediction::motionCompensation", "symbolSize": "22", "x": -606.0065800619402, "y": 87.9753244084331, "category": 0, "url": "http://www.baidu.com", "description": "运动补偿"}, {"id": "36", "name": "PU::spanMotionInfo", "symbolSize": "20", "x": 62.62672863924462, "y": 188.84553435004113, "category": 0, "url": "http://www.baidu.com", "description": "TODO"}, {"id": "40", "name": "PU::getIBCMergeCandidates", "symbolSize": "21", "x": -228.97479546072861, "y": -292.14706961604145, "category": 0, "url": "http://www.baidu.com", "description": "获得IBC Merge模式候选"}, {"id": "46", "name": "PU::checkDMVRCondition", "symbolSize": "20", "x": 246.59340019648698, "y": -60.356106899645, "category": 0, "url": "http://www.baidu.com", "description": "TODO"}, {"id": "47", "name": "InterPrediction::xPredInterBi", "symbolSize": "21", "x": -452.3312131580724, "y": 242.88617570137328, "category": 0, "url": "http://www.baidu.com", "description": "执行双向预测"}, {"id": "48", "name": "IntraPrediction::geneWeightedPred", "symbolSize": "20", "x": -52.50777275582266, "y": -113.58826147902712, "category": 0, "url": "http://www.baidu.com", "description": "TODO"}, {"id": "50", "name": "PU::getInterMergeCandidates", "symbolSize": "21", "x": 9.451414922662138, "y": -65.05645808173824, "category": 0, "url": "https://liuxiangrui.github.io/2021/12/13/VTM%E4%BB%A3%E7%A0%81%E5%AD%A6%E4%B9%A0/PU_getInterMergeCandidates/", "description": "获得Merge模式候选"}, {"id": "51", "name": "PU::getInterMMVDMergeCandidates", "symbolSize": "20", "x": -148.36747326812105, "y": -197.08200460894182, "category": 0, "url": "http://www.baidu.com", "description": "获得MMVD Merge模式候选"}, {"id": "52", "name": "PU::getGeoMergeCandidates", "symbolSize": "21", "x": 96.50562227178636, "y": 29.399278316468894, "category": 0, "url": "http://www.baidu.com", "description": "获得Geo Merge模式候选"}, {"id": "56", "name": "updateCandList", "symbolSize": "20", "x": -233.04932934519002, "y": -90.68213670093775, "category": 0, "url": "https://liuxiangrui.github.io/2021/12/13/VTM%E4%BB%A3%E7%A0%81%E5%AD%A6%E4%B9%A0/updateCandList/", "description": "根据代价向列表插入新节点"}, {"id": "57", "name": "MergeCtx::setMmvdMergeCandiInfo", "symbolSize": "20", "x": 113.23297989296276, "y": -101.81449100385026, "category": 0, "url": "https://liuxiangrui.github.io/2021/12/13/VTM%E4%BB%A3%E7%A0%81%E5%AD%A6%E4%B9%A0/Class_MergeCtx/", "description": "将MMVD Merge模式MVP候选的运动信息复制到PU"}, {"id": "58", "name": "MergeCtx::setMergeInfo", "symbolSize": "20", "x": -122.59916114283317, "y": 26.87317209083625, "category": 0, "url": "https://liuxiangrui.github.io/2021/12/13/VTM%E4%BB%A3%E7%A0%81%E5%AD%A6%E4%B9%A0/Class_MergeCtx/", "description": "将Merge模式MVP候选的运动信息复制到PU"}, {"id": "59", "name": "PU::addMergeHMVPCand", "symbolSize": "20", "x": 92.33884314475387, "y": -84.3362946754774, "category": 0, "url": "https://liuxiangrui.github.io/2021/12/13/VTM%E4%BB%A3%E7%A0%81%E5%AD%A6%E4%B9%A0/PU_addMergeHMVPCand/", "description": "向Merge候选列表加入HMVP"}, {"id": "53", "name": "DecCu::xDeriveCUMV", "symbolSize": "26", "x": -268.7052121123146, "y": 13.839512521645162, "category": 2, "url": "http://www.baidu.com", "description": "TODO"}, {"id": "54", "name": "DecCu::xReconInter", "symbolSize": "21", "x": -448.4748305247553, "y": 263.21254736268247, "category": 2, "url": "http://www.baidu.com", "description": "TODO"}, {"id": "55", "name": "DecCu::xReconIntraQT", "symbolSize": "20", "x": -679.5270938249387, "y": 14.946608242072301, "category": 2, "url": "http://www.baidu.com", "description": "TODO"}, {"id": "5", "name": "EncApp::encodePrep", "symbolSize": "21", "x": -557.9798069364235, "y": 36.702506181849984, "category": 3, "url": "http://www.baidu.com", "description": "TODO"}, {"id": "6", "name": "EncApp::encode", "symbolSize": "22", "x": -490.5716610218301, "y": 140.04053301844684, "category": 3, "url": "http://www.baidu.com", "description": "CSV编码入口函数"}, {"id": "7", "name": "EncApp::xWriteOutput", "symbolSize": "20", "x": -559.2826667916427, "y": 71.63309118027504, "category": 3, "url": "http://www.baidu.com", "description": "向文件写入访问单元"}, {"id": "0", "name": "EncSlice::compressSlice", "symbolSize": "21", "x": -306.16044126850807, "y": -166.10495166845192, "category": 1, "url": "http://www.baidu.com", "description": "Slice编码入口"}, {"id": "1", "name": "EncGOP::compressGOP", "symbolSize": "29", "x": -464.6532783739154, "y": -198.78908000854852, "category": 1, "url": "http://www.baidu.com", "description": "GOP编码入口"}, {"id": "2", "name": "EncLib::encode", "symbolSize": "21", "x": -526.0258558343527, "y": -37.5814649812919, "category": 1, "url": "http://www.baidu.com", "description": "CSV编码入口"}, {"id": "3", "name": "EncGOP::applyDeblockingFilterMetric", "symbolSize": "20", "x": -568.8341116478272, "y": -100.32542478670575, "category": 1, "url": "http://www.baidu.com", "description": "TODO"}, {"id": "4", "name": "EncLib::encodePrep", "symbolSize": "21", "x": -722.435795769145, "y": 30.018085081420352, "category": 1, "url": "http://www.baidu.com", "description": "TODO"}, {"id": "8", "name": "DeblockingFilter::deblockingFilterPic", "symbolSize": "20", "x": -531.5812827864164, "y": 13.058363569358391, "category": 1, "url": "http://www.baidu.com", "description": "进行去块效应滤波"}, {"id": "9", "name": "EncSlice::encodeSlice", "symbolSize": "20", "x": -530.5515981055962, "y": -293.9134704287359, "category": 1, "url": "http://www.baidu.com", "description": "Slice编码入口"}, {"id": "10", "name": "EncGOP::xWriteParameterSets", "symbolSize": "20", "x": -706.8286159208144, "y": -24.552188001372656, "category": 1, "url": "http://www.baidu.com", "description": "向比特流写入参数集"}, {"id": "11", "name": "EncGOP::xWritePicHeader", "symbolSize": "20", "x": -291.5372367115898, "y": -13.454532962925668, "category": 1, "url": "http://www.baidu.com", "description": "向比特流写入图像头信息"}, {"id": "12", "name": "HLSWriter::codeSliceHeader", "symbolSize": "20", "x": -655.8528851979108, "y": -84.21287285385023, "category": 1, "url": "http://www.baidu.com", "description": "向比特流写入Slice头信息"}, {"id": "13", "name": "EncSlice::encodeCtus", "symbolSize": "22", "x": -376.0958642763418, "y": -191.6751217886846, "category": 1, "url": "http://www.baidu.com", "description": "CTU编码入口"}, {"id": "15", "name": "EncGOP::xCalculateAddPSNRs", "symbolSize": "20", "x": -498.000643887077, "y": -234.49099502052832, "category": 1, "url": "http://www.baidu.com", "description": "计算GOP的PSNR"}, {"id": "16", "name": "EncCu::compressCtu", "symbolSize": "21", "x": -455.7697121433366, "y": -197.6999904568964, "category": 1, "url": "http://www.baidu.com", "description": "CTU编码入口"}, {"id": "18", "name": "EncCu::xCompressCU", "symbolSize": "32", "x": -564.9675338965119, "y": -61.79388477978932, "category": 1, "url": "http://www.baidu.com", "description": "CU编码入口"}, {"id": "19", "name": "EncCu::xCheckModeSplit", "symbolSize": "24", "x": -346.2032295935929, "y": -86.81594384562197, "category": 1, "url": "http://www.baidu.com", "description": "检查划分模式"}, {"id": "20", "name": "EncCu::xCheckRDCostAffineMerge2Nx2N", "symbolSize": "25", "x": -823.8052438309644, "y": 207.04382485883968, "category": 1, "url": "http://www.baidu.com", "description": "检查Affine Merge模式"}, {"id": "21", "name": "EncCu::xCheckPLT", "symbolSize": "25", "x": -799.4874584388733, "y": -2.538976608590076, "category": 1, "url": "http://www.baidu.com", "description": "检查PLT模式"}, {"id": "22", "name": "EncCu::xCheckRDCostHashInter", "symbolSize": "23", "x": -481.66940536666135, "y": -125.24069558061714, "category": 1, "url": "http://www.baidu.com", "description": "检查Hash Inter模式"}, {"id": "23", "name": "EncCu::xCheckRDCostIBCMode", "symbolSize": "27", "x": -791.0244507367182, "y": -278.9181756054485, "category": 1, "url": "http://www.baidu.com", "description": "检查IBC模式"}, {"id": "24", "name": "EncCu::xCheckRDCostIBCModeMerge2Nx2N", "symbolSize": "29", "x": -471.920193611168, "y": -111.8017737815851, "category": 1, "url": "http://www.baidu.com", "description": "检查IBC Merge模式"}, {"id": "25", "name": "EncCu::xCheckRDCostInter", "symbolSize": "23", "x": -831.7192701924816, "y": -185.6361530436825, "category": 1, "url": "http://www.baidu.com", "description": "检查Inter模式"}, {"id": "26", "name": "EncCu::xCheckRDCostInterIMV", "symbolSize": "23", "x": -664.2992035054078, "y": -6.221013250536544, "category": 1, "url": "http://www.baidu.com", "description": "检查Inter IMV模式"}, {"id": "27", "name": "EncCu::xCheckRDCostIntra", "symbolSize": "27", "x": -487.9323977919536, "y": -26.655838077320652, "category": 1, "url": "http://www.baidu.com", "description": "检查Intra模式"}, {"id": "28", "name": "EncCu::xCheckRDCostMerge2Nx2N", "symbolSize": "31", "x": -425.5120221125235, "y": -114.29315226705839, "category": 1, "url": "https://liuxiangrui.github.io/2021/12/13/VTM%E4%BB%A3%E7%A0%81%E5%AD%A6%E4%B9%A0/EncCU_xCheckRDCostMerge2Nx2N/", "description": "使用率失真优化选择Merge模式最优MVP"}, {"id": "29", "name": "EncCu::xCheckRDCostMergeGeo2Nx2N", "symbolSize": "25", "x": -827.136926128985, "y": 96.00415123173758, "category": 1, "url": "http://www.baidu.com", "description": "检查Merge Geo模式"}, {"id": "30", "name": "EncCu::xReuseCachedResult", "symbolSize": "28", "x": -436.2270805104839, "y": 109.30928102341846, "category": 1, "url": "http://www.baidu.com", "description": "复用缓存结果"}, {"id": "31", "name": "EncCu::xCheckBestMode", "symbolSize": "20", "x": -756.4731088291713, "y": -198.57143691304637, "category": 1, "url": "http://www.baidu.com", "description": "更新最优模式"}, {"id": "32", "name": "EncCu::xEncodeDontSplit", "symbolSize": "20", "x": -401.6679912867579, "y": -151.61833256673668, "category": 1, "url": "http://www.baidu.com", "description": "TODO"}, {"id": "33", "name": "EncCu::xCalDebCost", "symbolSize": "20", "x": -426.2436157769327, "y": -160.59523415036378, "category": 1, "url": "http://www.baidu.com", "description": "TODO"}, {"id": "34", "name": "EncCu::xCheckChromaQPOffset", "symbolSize": "20", "x": -752.4907496881605, "y": -105.94059506406832, "category": 1, "url": "http://www.baidu.com", "description": "检查色度QP偏移量"}, {"id": "37", "name": "EncCu::xEncodeInterResidual", "symbolSize": "24", "x": -702.4965172874527, "y": -3.164515177916286, "category": 1, "url": "http://www.baidu.com", "description": "编码帧间预测残差"}, {"id": "38", "name": "InterSearch::predInterHashSearch", "symbolSize": "21", "x": -358.0539796249045, "y": 66.91976983346012, "category": 1, "url": "http://www.baidu.com", "description": "TODO"}, {"id": "39", "name": "InterSearch::encodeResAndCalcRdInterCU", "symbolSize": "20", "x": -594.2664461780166, "y": -79.72206243015907, "category": 1, "url": "http://www.baidu.com", "description": "TODO"}, {"id": "41", "name": "InterSearch::searchBv", "symbolSize": "20", "x": -326.8408799135906, "y": -29.11673851447148, "category": 1, "url": "http://www.baidu.com", "description": "TODO"}, {"id": "42", "name": "EncCu::xCheckDQP", "symbolSize": "20", "x": -401.04809930279714, "y": -195.65434051266445, "category": 1, "url": "http://www.baidu.com", "description": "TODO"}, {"id": "43", "name": "InterSearch::predInterSearch", "symbolSize": "21", "x": -869.3742955111773, "y": -104.83392344999822, "category": 1, "url": "http://www.baidu.com", "description": "搜索最优帧间预测候选"}, {"id": "44", "name": "IntraSearch::estIntraPredChromaQT", "symbolSize": "20", "x": -305.6715737267308, "y": 20.230684774035325, "category": 1, "url": "http://www.baidu.com", "description": "TODO"}, {"id": "45", "name": "IntraSearch::estIntraPredLumaQT", "symbolSize": "22", "x": -617.4666395535405, "y": -170.17307439787638, "category": 1, "url": "http://www.baidu.com", "description": "TODO"}, {"id": "49", "name": "InterSearch::xCalcPuMeBits", "symbolSize": "20", "x": -636.5594321576388, "y": -128.38115562993133, "category": 1, "url": "http://www.baidu.com", "description": "计算PU的Merge标志位比特"}, {"id": "60", "name": "IntraSearch::reduceHadCandList", "symbolSize": "21", "x": -709.5154653574994, "y": -282.06440287182, "category": 1, "url": "http://www.baidu.com", "description": "TODO"}], "links": [{"source": "1", "target": "0"}, {"source": "2", "target": "1"}, {"source": "4", "target": "1"}, {"source": "6", "target": "2"}, {"source": "1", "target": "3"}, {"source": "5", "target": "4"}, {"source": "6", "target": "7"}, {"source": "1", "target": "8"}, {"source": "1", "target": "9"}, {"source": "1", "target": "10"}, {"source": "1", "target": "11"}, {"source": "1", "target": "12"}, {"source": "0", "target": "13"}, {"source": "1", "target": "14"}, {"source": "1", "target": "15"}, {"source": "13", "target": "16"}, {"source": "13", "target": "17"}, {"source": "16", "target": "18"}, {"source": "19", "target": "18"}, {"source": "18", "target": "19"}, {"source": "18", "target": "20"}, {"source": "18", "target": "21"}, {"source": "18", "target": "22"}, {"source": "18", "target": "23"}, {"source": "18", "target": "24"}, {"source": "18", "target": "25"}, {"source": "18", "target": "26"}, {"source": "18", "target": "27"}, {"source": "18", "target": "28"}, {"source": "18", "target": "29"}, {"source": "18", "target": "30"}, {"source": "19", "target": "31"}, {"source": "21", "target": "31"}, {"source": "23", "target": "31"}, {"source": "24", "target": "31"}, {"source": "27", "target": "31"}, {"source": "37", "target": "31"}, {"source": "30", "target": "31"}, {"source": "21", "target": "32"}, {"source": "23", "target": "32"}, {"source": "24", "target": "32"}, {"source": "27", "target": "32"}, {"source": "37", "target": "32"}, {"source": "30", "target": "32"}, {"source": "21", "target": "33"}, {"source": "20", "target": "33"}, {"source": "22", "target": "33"}, {"source": "23", "target": "33"}, {"source": "24", "target": "33"}, {"source": "25", "target": "33"}, {"source": "26", "target": "33"}, {"source": "27", "target": "33"}, {"source": "28", "target": "33"}, {"source": "29", "target": "33"}, {"source": "30", "target": "33"}, {"source": "19", "target": "34"}, {"source": "21", "target": "34"}, {"source": "23", "target": "34"}, {"source": "24", "target": "34"}, {"source": "27", "target": "34"}, {"source": "37", "target": "34"}, {"source": "30", "target": "34"}, {"source": "20", "target": "35"}, {"source": "20", "target": "36"}, {"source": "23", "target": "36"}, {"source": "24", "target": "36"}, {"source": "38", "target": "36"}, {"source": "43", "target": "36"}, {"source": "28", "target": "36"}, {"source": "29", "target": "36"}, {"source": "53", "target": "36"}, {"source": "20", "target": "37"}, {"source": "22", "target": "37"}, {"source": "25", "target": "37"}, {"source": "26", "target": "37"}, {"source": "28", "target": "37"}, {"source": "29", "target": "37"}, {"source": "22", "target": "38"}, {"source": "23", "target": "39"}, {"source": "24", "target": "39"}, {"source": "24", "target": "40"}, {"source": "24", "target": "41"}, {"source": "19", "target": "42"}, {"source": "21", "target": "42"}, {"source": "23", "target": "42"}, {"source": "24", "target": "42"}, {"source": "27", "target": "42"}, {"source": "37", "target": "42"}, {"source": "30", "target": "42"}, {"source": "25", "target": "43"}, {"source": "26", "target": "43"}, {"source": "27", "target": "44"}, {"source": "27", "target": "45"}, {"source": "35", "target": "46"}, {"source": "28", "target": "46"}, {"source": "47", "target": "46"}, {"source": "35", "target": "47"}, {"source": "28", "target": "48"}, {"source": "54", "target": "48"}, {"source": "28", "target": "49"}, {"source": "28", "target": "50"}, {"source": "53", "target": "50"}, {"source": "52", "target": "50"}, {"source": "28", "target": "51"}, {"source": "53", "target": "51"}, {"source": "29", "target": "52"}, {"source": "53", "target": "52"}, {"source": "30", "target": "53"}, {"source": "30", "target": "54"}, {"source": "30", "target": "55"}, {"source": "28", "target": "56"}, {"source": "20", "target": "56"}, {"source": "45", "target": "56"}, {"source": "60", "target": "56"}, {"source": "28", "target": "57"}, {"source": "53", "target": "57"}, {"source": "29", "target": "58"}, {"source": "28", "target": "58"}, {"source": "53", "target": "58"}, {"source": "50", "target": "59"}, {"source": "40", "target": "59"}, {"source": "45", "target": "60"}], "categories": [{"name": "CommonLib"}, {"name": "EncoderLib"}, {"name": "DecoderLib"}, {"name": "EncoderApp"}, {"name": "DecoderApp"}]}